{"JpY1ot4oolgVUt5T5MhafQ==":"whatsapp-image-2022-02-16-at-17.33.45.jpeg","4albf2oBisrSJU9QV0vijg==":"mbr.png","aLe3ib2+qCfQV5ylB4NP4w==":"value-of-time-essay.png","/9EX7tfZYRc1yoEyAZwMwA==":"two-time-value-of-money-formulas-57a520e15f9b58974aa1f9f4.jpg","8vkOdoJssmmOMwD0wh84cQ==":"mbr-1.png","mSsX9WKgqddjIXFciBYULw==":"mbr.jpg","InJ7LxuQ7pjH7tf8rYsB7Q==":"whatsapp-image-2022-02-17-at-20.18.29.jpeg","GsB9hKcaT5AQFYt3kMnw7A==":"whatsapp-image-2022-02-17-at-21.47.52.jpeg","vBiNTtJJvP/U1oQWeNKIiA==":"whatsapp-image-2022-02-17-at-20.18.29-1.jpeg","/IiwzGo40x43Ah+hLgwiJg==":"whatsapp-image-2022-02-17-at-21.47.52-1.jpeg","aYgTVZQ4i2y7uXUbJMKOEA==":"whatsapp-image-2022-02-17-at-20.18.29-2.jpeg","uVAbDP/4BVS+u2rDSHUYnQ==":"whatsapp-image-2022-02-17-at-20.18.29-3.jpeg","froOLifqXqTCqfPyjst5+A==":"whatsapp-image-2022-02-17-at-21.47.52-2.jpeg","a4qFJkTb/mrxOwGLFxjr/w==":"whatsapp-image-2022-02-17-at-23.17.41.jpeg","Opr3Fhys9Lro/tqYyjkVag==":"whatsapp-image-2022-02-17-at-23.17.41-1.jpeg","snShjaS0VJ+o8ClCr7aXeA==":"whatsapp-image-2022-02-17-at-21.47.52-3.jpeg","4daao42sjZ2WQ1ApKdkXcg==":"whatsapp-image-2022-02-17-at-23.28.01.jpeg","AwKNeFuFdmr1d0chny0Dug==":"whatsapp-image-2022-02-17-at-21.47.52-4.jpeg","UnYU4KWevZMSVS9BmsT95A==":"whatsapp-image-2022-02-17-at-21.47.52-5.jpeg","HZbAVz2R14wAmTR+tmwN5A==":"whatsapp-image-2022-02-17-at-23.28.01-1.jpeg","2QUZo4JW7V3WQZwLLSMPOg==":"whatsapp-image-2022-02-17-at-23.17.41-2.jpeg","CIR5OBHXZtL0Xm5G0pqjzg==":"whatsapp-image-2022-02-17-at-23.28.01-2.jpeg","N+mTz2uT2cFliARreJPiyA==":"whatsapp-image-2022-02-17-at-23.28.01-3.jpeg","6l3UWDzkriLqlxXLBh6ftg==":"whatsapp-image-2022-02-17-at-23.28.01-4.jpeg","A2sK2peczEQjuxo1oLyZoQ==":"whatsapp-image-2022-02-17-at-21.44.18.jpeg","6wHL7zYJt+VMZpu8LLo3hQ==":"whatsapp-image-2022-02-17-at-23.43.48.jpeg","2oG8wBgKl7+zJdnzqZ09iA==":"whatsapp-image-2022-02-17-at-21.47.52-6.jpeg","VVNsFhkv+v8phl0o2fc6gw==":"whatsapp-image-2022-02-17-at-21.44.18-1.jpeg","snb0WHGxp3glz+PL3N76Og==":"kirrraa.jpg"}